assets/__init__.py
assets/ascii_logo1.txt
assets/ascii_logo2.txt
lib/__init__.py
lib/forward.py
lib/shell.py
resources/__init__.py
resources/ascii_logo1.txt
resources/ascii_logo2.txt
resources/unio-server-2.1.0.zip
resources/unio-server-2.1.1.zip
resources/unio-server-2.1.2.zip
resources/unio.key
resources/unio2.key
unio/__init__.py
unio/client.py
unio/hostname.py
unio/install.py
unio/log.py
unio/main.py
unio/network.py
unio/properties.py
unio/restart.py
unio/shell.py
unio/speedtest.py
unio/sync.py
unio/utils.py
unio/wifi.py
unio_cli-0.2.1.dist-info/LICENSE.txt
unio_cli-0.2.1.dist-info/METADATA
unio_cli-0.2.1.dist-info/WHEEL
unio_cli-0.2.1.dist-info/entry_points.txt
unio_cli-0.2.1.dist-info/top_level.txt
unio_cli-0.2.1.dist-info/RECORD
